{
  "scrape_date": "2025-08-19T04:32:28.595011",
  "total_products": 34,
  "products": [
    {
      "title": "Unknown Product",
      "brand": "Unknown",
      "price": "$95.00",
      "original_price": "$95.00",
      "url": "https://www.therealreal.com/products/women/shoes/sneakers/junya-watanabe-comme-des-garcons-man-x-baracuta-patent-leather-sneakers-r685g",
      "image_url": "https://www.therealreal.comdata:image/svg+xml;charset=utf-8,%3Csvg%20xmlns%3D%27http%3A%2F%2Fwww.w3.org%2F2000%2Fsvg%27%20width%3D%27220%27%20height%3D%27290%27%3E%3Crect%20width%3D%27100%25%27%20height%3D%27100%25%27%20style%3D%27fill%3A%20white%27%2F%3E%3C%2Fsvg%3E",
      "size": "Women's Size: 8",
      "condition": "N/A"
    },
    {
      "title": "Unknown Product",
      "brand": "Unknown",
      "price": "$65.00",
      "original_price": "$65.00",
      "url": "https://www.therealreal.com/products/women/clothing/loungewear/junya-watanabe-sweatpants-r6059",
      "image_url": "https://www.therealreal.comdata:image/svg+xml;charset=utf-8,%3Csvg%20xmlns%3D%27http%3A%2F%2Fwww.w3.org%2F2000%2Fsvg%27%20width%3D%27220%27%20height%3D%27290%27%3E%3Crect%20width%3D%27100%25%27%20height%3D%27100%25%27%20style%3D%27fill%3A%20white%27%2F%3E%3C%2Fsvg%3E",
      "size": "Size: XS",
      "condition": "N/A"
    },
    {
      "title": "Unknown Product",
      "brand": "Unknown",
      "price": "$65.00",
      "original_price": "$65.00",
      "url": "https://www.therealreal.com/products/women/clothing/pants/junya-watanabe-comme-des-garcons-wool-wide-leg-pants-qxbxr",
      "image_url": "https://www.therealreal.comdata:image/svg+xml;charset=utf-8,%3Csvg%20xmlns%3D%27http%3A%2F%2Fwww.w3.org%2F2000%2Fsvg%27%20width%3D%27220%27%20height%3D%27290%27%3E%3Crect%20width%3D%27100%25%27%20height%3D%27100%25%27%20style%3D%27fill%3A%20white%27%2F%3E%3C%2Fsvg%3E",
      "size": "Size: S",
      "condition": "N/A"
    },
    {
      "title": "Unknown Product",
      "brand": "Unknown",
      "price": "$85.00",
      "original_price": "$85.00",
      "url": "https://www.therealreal.com/products/men/clothing/lounge-and-sleepwear/eye-junya-watanabe-comme-des-garcons-man-x-champion-lounge-bottoms-qzp6l",
      "image_url": "https://www.therealreal.comdata:image/svg+xml;charset=utf-8,%3Csvg%20xmlns%3D%27http%3A%2F%2Fwww.w3.org%2F2000%2Fsvg%27%20width%3D%27220%27%20height%3D%27290%27%3E%3Crect%20width%3D%27100%25%27%20height%3D%27100%25%27%20style%3D%27fill%3A%20white%27%2F%3E%3C%2Fsvg%3E",
      "size": "Size: M",
      "condition": "N/A"
    },
    {
      "title": "Unknown Product",
      "brand": "Unknown",
      "price": "$85.00",
      "original_price": "$85.00",
      "url": "https://www.therealreal.com/products/women/clothing/tops/junya-watanabe-comme-des-garcons-2013-striped-top-qel6s",
      "image_url": "https://www.therealreal.comdata:image/svg+xml;charset=utf-8,%3Csvg%20xmlns%3D%27http%3A%2F%2Fwww.w3.org%2F2000%2Fsvg%27%20width%3D%27220%27%20height%3D%27290%27%3E%3Crect%20width%3D%27100%25%27%20height%3D%27100%25%27%20style%3D%27fill%3A%20white%27%2F%3E%3C%2Fsvg%3E",
      "size": "Size: M",
      "condition": "N/A"
    },
    {
      "title": "Unknown Product",
      "brand": "Unknown",
      "price": "$60.00",
      "original_price": "$60.00",
      "url": "https://www.therealreal.com/products/women/shoes/sneakers/junya-watanabe-x-reebok-patent-leather-sneakers-r1l7m",
      "image_url": "https://www.therealreal.comdata:image/svg+xml;charset=utf-8,%3Csvg%20xmlns%3D%27http%3A%2F%2Fwww.w3.org%2F2000%2Fsvg%27%20width%3D%27220%27%20height%3D%27290%27%3E%3Crect%20width%3D%27100%25%27%20height%3D%27100%25%27%20style%3D%27fill%3A%20white%27%2F%3E%3C%2Fsvg%3E",
      "size": "Women's Size: 6",
      "condition": "N/A"
    },
    {
      "title": "Unknown Product",
      "brand": "Unknown",
      "price": "$95.00",
      "original_price": "$95.00",
      "url": "https://www.therealreal.com/products/women/clothing/tops/comme-des-garcons-play-graphic-print-crew-neck-t-shirt-r7rmg",
      "image_url": "https://www.therealreal.comdata:image/svg+xml;charset=utf-8,%3Csvg%20xmlns%3D%27http%3A%2F%2Fwww.w3.org%2F2000%2Fsvg%27%20width%3D%27220%27%20height%3D%27290%27%3E%3Crect%20width%3D%27100%25%27%20height%3D%27100%25%27%20style%3D%27fill%3A%20white%27%2F%3E%3C%2Fsvg%3E",
      "size": "Size: L",
      "condition": "N/A"
    },
    {
      "title": "Unknown Product",
      "brand": "Unknown",
      "price": "$95.00",
      "original_price": "$95.00",
      "url": "https://www.therealreal.com/products/men/clothing/t-shirts/comme-des-garcons-play-crew-neck-short-sleeve-t-shirt-r4oec",
      "image_url": "https://www.therealreal.comdata:image/svg+xml;charset=utf-8,%3Csvg%20xmlns%3D%27http%3A%2F%2Fwww.w3.org%2F2000%2Fsvg%27%20width%3D%27220%27%20height%3D%27290%27%3E%3Crect%20width%3D%27100%25%27%20height%3D%27100%25%27%20style%3D%27fill%3A%20white%27%2F%3E%3C%2Fsvg%3E",
      "size": "Size: XL",
      "condition": "N/A"
    },
    {
      "title": "Unknown Product",
      "brand": "Unknown",
      "price": "$80.00",
      "original_price": "$80.00",
      "url": "https://www.therealreal.com/products/women/clothing/tops/comme-des-garcons-play-graphic-print-crew-neck-t-shirt-r5zux",
      "image_url": "https://www.therealreal.comdata:image/svg+xml;charset=utf-8,%3Csvg%20xmlns%3D%27http%3A%2F%2Fwww.w3.org%2F2000%2Fsvg%27%20width%3D%27220%27%20height%3D%27290%27%3E%3Crect%20width%3D%27100%25%27%20height%3D%27100%25%27%20style%3D%27fill%3A%20white%27%2F%3E%3C%2Fsvg%3E",
      "size": "Size: S",
      "condition": "N/A"
    },
    {
      "title": "Unknown Product",
      "brand": "Unknown",
      "price": "$85.00",
      "original_price": "$85.00",
      "url": "https://www.therealreal.com/products/women/clothing/tops/comme-des-garcons-play-graphic-print-crew-neck-t-shirt-r8kln",
      "image_url": "https://www.therealreal.comdata:image/svg+xml;charset=utf-8,%3Csvg%20xmlns%3D%27http%3A%2F%2Fwww.w3.org%2F2000%2Fsvg%27%20width%3D%27220%27%20height%3D%27290%27%3E%3Crect%20width%3D%27100%25%27%20height%3D%27100%25%27%20style%3D%27fill%3A%20white%27%2F%3E%3C%2Fsvg%3E",
      "size": "Size: L",
      "condition": "N/A"
    },
    {
      "title": "Unknown Product",
      "brand": "Unknown",
      "price": "$85.00",
      "original_price": "$85.00",
      "url": "https://www.therealreal.com/products/women/accessories/wallets/comme-des-garcons-leather-wallet-r6fvg",
      "image_url": "https://www.therealreal.comdata:image/svg+xml;charset=utf-8,%3Csvg%20xmlns%3D%27http%3A%2F%2Fwww.w3.org%2F2000%2Fsvg%27%20width%3D%27220%27%20height%3D%27290%27%3E%3Crect%20width%3D%27100%25%27%20height%3D%27100%25%27%20style%3D%27fill%3A%20white%27%2F%3E%3C%2Fsvg%3E",
      "size": "N/A",
      "condition": "N/A"
    },
    {
      "title": "Unknown Product",
      "brand": "Unknown",
      "price": "$85.00",
      "original_price": "$85.00",
      "url": "https://www.therealreal.com/products/men/clothing/t-shirts/comme-des-garcons-crew-neck-short-sleeve-t-shirt-r6j5j",
      "image_url": "https://www.therealreal.comdata:image/svg+xml;charset=utf-8,%3Csvg%20xmlns%3D%27http%3A%2F%2Fwww.w3.org%2F2000%2Fsvg%27%20width%3D%27220%27%20height%3D%27290%27%3E%3Crect%20width%3D%27100%25%27%20height%3D%27100%25%27%20style%3D%27fill%3A%20white%27%2F%3E%3C%2Fsvg%3E",
      "size": "Size: S",
      "condition": "N/A"
    },
    {
      "title": "Unknown Product",
      "brand": "Unknown",
      "price": "$95.00",
      "original_price": "$95.00",
      "url": "https://www.therealreal.com/products/men/clothing/t-shirts/comme-des-garcons-play-graphic-print-crew-neck-t-shirt-r5swc",
      "image_url": "https://www.therealreal.comdata:image/svg+xml;charset=utf-8,%3Csvg%20xmlns%3D%27http%3A%2F%2Fwww.w3.org%2F2000%2Fsvg%27%20width%3D%27220%27%20height%3D%27290%27%3E%3Crect%20width%3D%27100%25%27%20height%3D%27100%25%27%20style%3D%27fill%3A%20white%27%2F%3E%3C%2Fsvg%3E",
      "size": "Size: M",
      "condition": "N/A"
    },
    {
      "title": "Unknown Product",
      "brand": "Unknown",
      "price": "$75.00",
      "original_price": "$75.00",
      "url": "https://www.therealreal.com/products/men/clothing/t-shirts/comme-des-garcons-play-graphic-print-crew-neck-t-shirt-r600q",
      "image_url": "https://www.therealreal.comdata:image/svg+xml;charset=utf-8,%3Csvg%20xmlns%3D%27http%3A%2F%2Fwww.w3.org%2F2000%2Fsvg%27%20width%3D%27220%27%20height%3D%27290%27%3E%3Crect%20width%3D%27100%25%27%20height%3D%27100%25%27%20style%3D%27fill%3A%20white%27%2F%3E%3C%2Fsvg%3E",
      "size": "Size: S",
      "condition": "N/A"
    },
    {
      "title": "Unknown Product",
      "brand": "Unknown",
      "price": "$85.00",
      "original_price": "$85.00",
      "url": "https://www.therealreal.com/products/men/clothing/t-shirts/comme-des-garcons-play-graphic-print-crew-neck-t-shirt-r7t83",
      "image_url": "https://www.therealreal.comdata:image/svg+xml;charset=utf-8,%3Csvg%20xmlns%3D%27http%3A%2F%2Fwww.w3.org%2F2000%2Fsvg%27%20width%3D%27220%27%20height%3D%27290%27%3E%3Crect%20width%3D%27100%25%27%20height%3D%27100%25%27%20style%3D%27fill%3A%20white%27%2F%3E%3C%2Fsvg%3E",
      "size": "Size: L",
      "condition": "N/A"
    },
    {
      "title": "Unknown Product",
      "brand": "Unknown",
      "price": "$85.00",
      "original_price": "$85.00",
      "url": "https://www.therealreal.com/products/women/shoes/sneakers/comme-des-garcons-play-x-converse-canvas-printed-sneakers-r1u1d",
      "image_url": "https://www.therealreal.comdata:image/svg+xml;charset=utf-8,%3Csvg%20xmlns%3D%27http%3A%2F%2Fwww.w3.org%2F2000%2Fsvg%27%20width%3D%27220%27%20height%3D%27290%27%3E%3Crect%20width%3D%27100%25%27%20height%3D%27100%25%27%20style%3D%27fill%3A%20white%27%2F%3E%3C%2Fsvg%3E",
      "size": "Women's Size: 7",
      "condition": "N/A"
    },
    {
      "title": "Unknown Product",
      "brand": "Unknown",
      "price": "$85.00",
      "original_price": "$85.00",
      "url": "https://www.therealreal.com/products/men/shoes/sneakers/comme-des-garcons-play-x-converse-canvas-printed-sneakers-r6e2n",
      "image_url": "https://www.therealreal.comdata:image/svg+xml;charset=utf-8,%3Csvg%20xmlns%3D%27http%3A%2F%2Fwww.w3.org%2F2000%2Fsvg%27%20width%3D%27220%27%20height%3D%27290%27%3E%3Crect%20width%3D%27100%25%27%20height%3D%27100%25%27%20style%3D%27fill%3A%20white%27%2F%3E%3C%2Fsvg%3E",
      "size": "Men's Size: 10",
      "condition": "N/A"
    },
    {
      "title": "Unknown Product",
      "brand": "Unknown",
      "price": "$85.00",
      "original_price": "$85.00",
      "url": "https://www.therealreal.com/products/women/clothing/tops/comme-des-garcons-play-striped-crew-neck-top-r6zov",
      "image_url": "https://www.therealreal.comdata:image/svg+xml;charset=utf-8,%3Csvg%20xmlns%3D%27http%3A%2F%2Fwww.w3.org%2F2000%2Fsvg%27%20width%3D%27220%27%20height%3D%27290%27%3E%3Crect%20width%3D%27100%25%27%20height%3D%27100%25%27%20style%3D%27fill%3A%20white%27%2F%3E%3C%2Fsvg%3E",
      "size": "Size: S",
      "condition": "N/A"
    },
    {
      "title": "Unknown Product",
      "brand": "Unknown",
      "price": "$35.00",
      "original_price": "$35.00",
      "url": "https://www.therealreal.com/products/men/clothing/t-shirts/comme-des-garcons-shirt-x-spalwart-crew-neck-short-sleeve-henley-r6b7y",
      "image_url": "https://www.therealreal.comdata:image/svg+xml;charset=utf-8,%3Csvg%20xmlns%3D%27http%3A%2F%2Fwww.w3.org%2F2000%2Fsvg%27%20width%3D%27220%27%20height%3D%27290%27%3E%3Crect%20width%3D%27100%25%27%20height%3D%27100%25%27%20style%3D%27fill%3A%20white%27%2F%3E%3C%2Fsvg%3E",
      "size": "Size: L",
      "condition": "N/A"
    },
    {
      "title": "Unknown Product",
      "brand": "Unknown",
      "price": "$80.00",
      "original_price": "$80.00",
      "url": "https://www.therealreal.com/products/men/clothing/t-shirts/comme-des-garcons-play-crew-neck-short-sleeve-t-shirt-r65j4",
      "image_url": "https://www.therealreal.comdata:image/svg+xml;charset=utf-8,%3Csvg%20xmlns%3D%27http%3A%2F%2Fwww.w3.org%2F2000%2Fsvg%27%20width%3D%27220%27%20height%3D%27290%27%3E%3Crect%20width%3D%27100%25%27%20height%3D%27100%25%27%20style%3D%27fill%3A%20white%27%2F%3E%3C%2Fsvg%3E",
      "size": "Size: L",
      "condition": "N/A"
    },
    {
      "title": "Unknown Product",
      "brand": "Unknown",
      "price": "$80.00",
      "original_price": "$80.00",
      "url": "https://www.therealreal.com/products/women/clothing/pants/black-comme-des-garcons-straight-leg-pants-r6pwy",
      "image_url": "https://www.therealreal.comdata:image/svg+xml;charset=utf-8,%3Csvg%20xmlns%3D%27http%3A%2F%2Fwww.w3.org%2F2000%2Fsvg%27%20width%3D%27220%27%20height%3D%27290%27%3E%3Crect%20width%3D%27100%25%27%20height%3D%27100%25%27%20style%3D%27fill%3A%20white%27%2F%3E%3C%2Fsvg%3E",
      "size": "Size: L",
      "condition": "N/A"
    },
    {
      "title": "Unknown Product",
      "brand": "Unknown",
      "price": "$95.00",
      "original_price": "$95.00",
      "url": "https://www.therealreal.com/products/men/clothing/t-shirts/comme-des-garcons-play-crew-neck-short-sleeve-t-shirt-r65ht",
      "image_url": "https://www.therealreal.comdata:image/svg+xml;charset=utf-8,%3Csvg%20xmlns%3D%27http%3A%2F%2Fwww.w3.org%2F2000%2Fsvg%27%20width%3D%27220%27%20height%3D%27290%27%3E%3Crect%20width%3D%27100%25%27%20height%3D%27100%25%27%20style%3D%27fill%3A%20white%27%2F%3E%3C%2Fsvg%3E",
      "size": "Size: L",
      "condition": "N/A"
    },
    {
      "title": "Unknown Product",
      "brand": "Unknown",
      "price": "$65.00",
      "original_price": "$65.00",
      "url": "https://www.therealreal.com/products/women/shoes/sneakers/cdg-x-the-north-face-nylon-sneakers-r41vt",
      "image_url": "https://www.therealreal.comdata:image/svg+xml;charset=utf-8,%3Csvg%20xmlns%3D%27http%3A%2F%2Fwww.w3.org%2F2000%2Fsvg%27%20width%3D%27220%27%20height%3D%27290%27%3E%3Crect%20width%3D%27100%25%27%20height%3D%27100%25%27%20style%3D%27fill%3A%20white%27%2F%3E%3C%2Fsvg%3E",
      "size": "Women's Size: 10",
      "condition": "N/A"
    },
    {
      "title": "Unknown Product",
      "brand": "Unknown",
      "price": "$80.00",
      "original_price": "$80.00",
      "url": "https://www.therealreal.com/products/women/shoes/sneakers/cdg-x-the-north-face-nylon-plaid-print-sneakers-qtgl1",
      "image_url": "https://www.therealreal.comdata:image/svg+xml;charset=utf-8,%3Csvg%20xmlns%3D%27http%3A%2F%2Fwww.w3.org%2F2000%2Fsvg%27%20width%3D%27220%27%20height%3D%27290%27%3E%3Crect%20width%3D%27100%25%27%20height%3D%27100%25%27%20style%3D%27fill%3A%20white%27%2F%3E%3C%2Fsvg%3E",
      "size": "Women's Size: 8",
      "condition": "N/A"
    },
    {
      "title": "Unknown Product",
      "brand": "Unknown",
      "price": "$55.00",
      "original_price": "$55.00",
      "url": "https://www.therealreal.com/products/women/shoes/sneakers/cdg-x-the-north-face-nylon-colorblock-pattern-sneakers-qtglp",
      "image_url": "https://www.therealreal.comdata:image/svg+xml;charset=utf-8,%3Csvg%20xmlns%3D%27http%3A%2F%2Fwww.w3.org%2F2000%2Fsvg%27%20width%3D%27220%27%20height%3D%27290%27%3E%3Crect%20width%3D%27100%25%27%20height%3D%27100%25%27%20style%3D%27fill%3A%20white%27%2F%3E%3C%2Fsvg%3E",
      "size": "Women's Size: 6",
      "condition": "N/A"
    },
    {
      "title": "Unknown Product",
      "brand": "Unknown",
      "price": "$70.00",
      "original_price": "$70.00",
      "url": "https://www.therealreal.com/products/women/clothing/tops/cdg-by-comme-des-garcons-striped-long-sleeve-button-up-top-q8hzq",
      "image_url": "https://www.therealreal.comdata:image/svg+xml;charset=utf-8,%3Csvg%20xmlns%3D%27http%3A%2F%2Fwww.w3.org%2F2000%2Fsvg%27%20width%3D%27220%27%20height%3D%27290%27%3E%3Crect%20width%3D%27100%25%27%20height%3D%27100%25%27%20style%3D%27fill%3A%20white%27%2F%3E%3C%2Fsvg%3E",
      "size": "Size: S",
      "condition": "N/A"
    },
    {
      "title": "See Similar",
      "brand": "Unknown",
      "price": "$50.00",
      "original_price": "$50.00",
      "url": "https://www.therealreal.com/similar/products/women/accessories/scarves-and-shawls/cdg-by-comme-des-garcons-polka-dot-print-shawl-qt7si?origin=shop",
      "image_url": "https://www.therealreal.comdata:image/svg+xml;charset=utf-8,%3Csvg%20xmlns%3D%27http%3A%2F%2Fwww.w3.org%2F2000%2Fsvg%27%20width%3D%27220%27%20height%3D%27290%27%3E%3Crect%20width%3D%27100%25%27%20height%3D%27100%25%27%20style%3D%27fill%3A%20white%27%2F%3E%3C%2Fsvg%3E",
      "size": "N/A",
      "condition": "N/A"
    },
    {
      "title": "See Similar",
      "brand": "Unknown",
      "price": "$95.00",
      "original_price": "$95.00",
      "url": "https://www.therealreal.com/similar/products/men/clothing/t-shirts/comme-des-garcons-graphic-print-crew-neck-t-shirt-qtwg1?origin=shop",
      "image_url": "https://www.therealreal.comdata:image/svg+xml;charset=utf-8,%3Csvg%20xmlns%3D%27http%3A%2F%2Fwww.w3.org%2F2000%2Fsvg%27%20width%3D%27220%27%20height%3D%27290%27%3E%3Crect%20width%3D%27100%25%27%20height%3D%27100%25%27%20style%3D%27fill%3A%20white%27%2F%3E%3C%2Fsvg%3E",
      "size": "Size: XL",
      "condition": "N/A"
    },
    {
      "title": "See Similar",
      "brand": "Unknown",
      "price": "$85.00",
      "original_price": "$85.00",
      "url": "https://www.therealreal.com/similar/products/men/clothing/t-shirts/cdg-by-comme-des-garcons-graphic-print-crew-neck-t-shirt-qje84?origin=shop",
      "image_url": "https://www.therealreal.comdata:image/svg+xml;charset=utf-8,%3Csvg%20xmlns%3D%27http%3A%2F%2Fwww.w3.org%2F2000%2Fsvg%27%20width%3D%27220%27%20height%3D%27290%27%3E%3Crect%20width%3D%27100%25%27%20height%3D%27100%25%27%20style%3D%27fill%3A%20white%27%2F%3E%3C%2Fsvg%3E",
      "size": "Size: S",
      "condition": "N/A"
    },
    {
      "title": "See Similar",
      "brand": "Unknown",
      "price": "$70.00",
      "original_price": "$70.00",
      "url": "https://www.therealreal.com/similar/products/men/accessories/wallets/cdg-by-comme-des-garcons-leather-coin-pouch-qf5hf?origin=shop",
      "image_url": "https://www.therealreal.comdata:image/svg+xml;charset=utf-8,%3Csvg%20xmlns%3D%27http%3A%2F%2Fwww.w3.org%2F2000%2Fsvg%27%20width%3D%27220%27%20height%3D%27290%27%3E%3Crect%20width%3D%27100%25%27%20height%3D%27100%25%27%20style%3D%27fill%3A%20white%27%2F%3E%3C%2Fsvg%3E",
      "size": "N/A",
      "condition": "N/A"
    },
    {
      "title": "See Similar",
      "brand": "Unknown",
      "price": "$60.00",
      "original_price": "$60.00",
      "url": "https://www.therealreal.com/similar/products/women/shoes/sneakers/comme-des-garcons-cdg-x-assc-animal-print-sneakers-qaau0?origin=shop",
      "image_url": "https://www.therealreal.comdata:image/svg+xml;charset=utf-8,%3Csvg%20xmlns%3D%27http%3A%2F%2Fwww.w3.org%2F2000%2Fsvg%27%20width%3D%27220%27%20height%3D%27290%27%3E%3Crect%20width%3D%27100%25%27%20height%3D%27100%25%27%20style%3D%27fill%3A%20white%27%2F%3E%3C%2Fsvg%3E",
      "size": "Women's Size: 8",
      "condition": "N/A"
    },
    {
      "title": "See Similar",
      "brand": "Unknown",
      "price": "$75.00",
      "original_price": "$75.00",
      "url": "https://www.therealreal.com/similar/products/women/clothing/tops/cdg-by-comme-des-garcons-graphic-print-crew-neck-t-shirt-pxo9g?origin=shop",
      "image_url": "https://www.therealreal.comdata:image/svg+xml;charset=utf-8,%3Csvg%20xmlns%3D%27http%3A%2F%2Fwww.w3.org%2F2000%2Fsvg%27%20width%3D%27220%27%20height%3D%27290%27%3E%3Crect%20width%3D%27100%25%27%20height%3D%27100%25%27%20style%3D%27fill%3A%20white%27%2F%3E%3C%2Fsvg%3E",
      "size": "Size: XS",
      "condition": "N/A"
    },
    {
      "title": "See Similar",
      "brand": "Unknown",
      "price": "$95.00",
      "original_price": "$95.00",
      "url": "https://www.therealreal.com/similar/products/women/clothing/tops/cdg-by-comme-des-garcons-striped-crew-neck-top-pok8k?origin=shop",
      "image_url": "https://www.therealreal.comdata:image/svg+xml;charset=utf-8,%3Csvg%20xmlns%3D%27http%3A%2F%2Fwww.w3.org%2F2000%2Fsvg%27%20width%3D%27220%27%20height%3D%27290%27%3E%3Crect%20width%3D%27100%25%27%20height%3D%27100%25%27%20style%3D%27fill%3A%20white%27%2F%3E%3C%2Fsvg%3E",
      "size": "Size: M",
      "condition": "N/A"
    },
    {
      "title": "Unknown Product",
      "brand": "Unknown",
      "price": "$60.00",
      "original_price": "$60.00",
      "url": "https://www.therealreal.com/products/women/clothing/tops/rick-owens-drkshdw-scoop-neck-short-sleeve-t-shirt-r12xf",
      "image_url": "https://www.therealreal.comdata:image/svg+xml;charset=utf-8,%3Csvg%20xmlns%3D%27http%3A%2F%2Fwww.w3.org%2F2000%2Fsvg%27%20width%3D%27220%27%20height%3D%27290%27%3E%3Crect%20width%3D%27100%25%27%20height%3D%27100%25%27%20style%3D%27fill%3A%20white%27%2F%3E%3C%2Fsvg%3E",
      "size": "Size: L",
      "condition": "N/A"
    }
  ]
}